MANIFEST.in
README.rst
setup.py
craption/__init__.py
craption/__init__.pyc
craption/cli.py
craption/cli.pyc
craption/settings.py
craption/settings.pyc
craption/upload.py
craption/upload.pyc
craption/utils.py
craption/utils.pyc
craption.egg-info/PKG-INFO
craption.egg-info/SOURCES.txt
craption.egg-info/dependency_links.txt
craption.egg-info/entry_points.txt
craption.egg-info/requires.txt
craption.egg-info/top_level.txt
craption/__pycache__/__init__.cpython-36.pyc
craption/__pycache__/cli.cpython-36.pyc
craption/__pycache__/settings.cpython-36.pyc
craption/__pycache__/upload.cpython-36.pyc
craption/__pycache__/utils.cpython-36.pyc