Metadata-Version: 1.0
Name: craption
Version: 1.5.0
Summary: Simple screenshot uploader
Home-page: https://github.com/jakehedman/CRAPtion
Author: Jakob Hedman
Author-email: jakob@hedman.email
License: GNU GPLv3
Platform: UNKNOWN
